nexusflowai/__init__.py
nexusflowai/_exceptions.py
nexusflowai/client.py
nexusflowai/utils.py
nexusflowai/resources/__init__.py
nexusflowai/resources/completions.py
nexusflowai/resources/models.py
nexusflowai/resources/utils.py
nexusflowai/resources/chat/__init__.py
nexusflowai/resources/chat/chat.py
nexusflowai/resources/chat/completions.py
nexusflowai/types/__init__.py
nexusflowai/types/chat_completion.py
nexusflowai/types/chat_completion_assistant_message_param.py
nexusflowai/types/chat_completion_chunk.py
nexusflowai/types/chat_completion_content_part_image_bytes_param.py
nexusflowai/types/chat_completion_create_params.py
nexusflowai/types/chat_completion_message.py
nexusflowai/types/chat_completion_message_param.py
nexusflowai/types/chat_completion_message_tool_call.py
nexusflowai/types/completion.py
nexusflowai/types/completion_choice.py
nexusflowai/types/completion_usage.py
nexusflowai/validators/__init__.py
nexusflowai/validators/base_input_validator.py
nexusflowai/validators/chat_completions_input_validator.py
nexusflowai/validators/completions_input_validator.py
nexusflowai/validators/json_schema_to_dataclasses.py
nexusflowai/validators/create_with_tools/__init__.py
nexusflowai/validators/create_with_tools/flow.py
nexusflowai/validators/create_with_tools/postprocess.py
nexusflowai/validators/create_with_tools/preprocess.py
nexusflowai/validators/create_with_tools/utils.py
nexusflowai/validators/qwen_agent/__init__.py
nexusflowai/validators/qwen_agent/flow.py
nexusflowai/validators/qwen_agent/qwen_message_translator.py
nexusflowai-0.2.3.dist-info/METADATA
nexusflowai-0.2.3.dist-info/WHEEL
nexusflowai-0.2.3.dist-info/licenses/LICENSE
nexusflowai-0.2.3.dist-info/RECORD
