Metadata-Version: 2.4
Name: nexusflowai
Version: 0.2.3
Summary: The official Python library for the nexusflowai API
Project-URL: Homepage, https://nexusflow.ai/
Project-URL: Repository, https://github.com/nexusflowai/NexusflowAI
Author: Nexusflow.ai
License-Expression: Apache-2.0
License-File: LICENSE
Classifier: Intended Audience :: Developers
Classifier: License :: OSI Approved :: Apache Software License
Classifier: Operating System :: MacOS
Classifier: Operating System :: Microsoft :: Windows
Classifier: Operating System :: OS Independent
Classifier: Operating System :: POSIX
Classifier: Operating System :: POSIX :: Linux
Classifier: Programming Language :: Python :: 3.10
Classifier: Programming Language :: Python :: 3.11
Classifier: Programming Language :: Python :: 3.12
Classifier: Topic :: Software Development :: Libraries :: Python Modules
Classifier: Typing :: Typed
Requires-Python: >=3.10
Requires-Dist: datamodel-code-generator==0.26.0
Requires-Dist: httpx<0.28.0
Requires-Dist: json-repair==0.29.4
Requires-Dist: jsonschema==4.23.0
Requires-Dist: openai==1.54.4
Requires-Dist: python-dateutil==2.9.0.post0
Requires-Dist: qwen-agent==0.0.13
Provides-Extra: dev
Requires-Dist: black==23.12.1; extra == 'dev'
Requires-Dist: pylint==3.0.3; extra == 'dev'
Requires-Dist: pytest-asyncio==0.23.8; extra == 'dev'
Requires-Dist: pytest-cov==5.0.0; extra == 'dev'
Requires-Dist: pytest-xdist==3.6.1; extra == 'dev'
Requires-Dist: pytest==7.4.3; extra == 'dev'
